{
  "checked": "Public Airbnb page · May 27, 2026",
  "url": "https://www.airbnb.co.uk/rooms/1559436233376573149",
  "title": "Well located, modern spacious house for 10 people.",
  "listingId": "1559436233376573149",
  "listingType": "Entire home in Ghent, Belgium",
  "rating": "5.0",
  "reviews": "20",
  "status": "Guest favourite · Top 5%",
  "host": "Veronique",
  "coHosts": [
    "Laurens"
  ],
  "quickFacts": [
    {
      "label": "Guests",
      "value": "10 maximum",
      "source": "airbnb-public"
    },
    {
      "label": "Bedrooms",
      "value": "3",
      "source": "airbnb-public"
    },
    {
      "label": "Beds",
      "value": "5",
      "source": "airbnb-public"
    },
    {
      "label": "Bathroom",
      "value": "1",
      "source": "airbnb-public"
    },
    {
      "label": "Check-in",
      "value": "After 16:00",
      "source": "airbnb-public"
    },
    {
      "label": "Checkout",
      "value": "Before 11:00",
      "source": "airbnb-public"
    }
  ],
  "guardrails": [
    "Public Airbnb facts were checked on May 27, 2026 without login.",
    "This listing was provided in Laurens’ account URL list, but its final public House of Wander collection name should be confirmed.",
    "Airbnb-hosted photos are catalogued only as references and are not displayed on the site.",
    "Live price, availability, cancellation, payment, and messaging remain on Airbnb."
  ]
}
